{"chunk_definitions":[{"chunk_id":"csetup_chunk","chunk_label":"setup","document_id":"286F9B27","expansion_state":0,"options":{"engine":"r","include":false,"label":"setup"},"row":11,"row_count":1,"visible":true},{"chunk_id":"c3tvtx6bgaops","chunk_label":"printAll","document_id":"286F9B27","expansion_state":0,"options":{"engine":"r","eval":true,"include":true,"label":"printAll"},"row":75,"row_count":1,"visible":true},{"chunk_id":"cyv2ohion397x","chunk_label":"demo1","document_id":"286F9B27","expansion_state":0,"options":{"engine":"r","eval":true,"include":true,"label":"demo1"},"row":89,"row_count":1,"visible":true},{"chunk_id":"ct6cposfqcish","chunk_label":"demo2","document_id":"286F9B27","expansion_state":0,"options":{"engine":"r","eval":true,"include":true,"label":"demo2"},"row":101,"row_count":1,"visible":true},{"chunk_id":"csn628g198a9s","chunk_label":"demo3.1","document_id":"286F9B27","expansion_state":0,"options":{"engine":"r","eval":true,"fig.height":5,"fig.width":12,"include":true,"label":"demo3.1"},"row":107,"row_count":1,"visible":true},{"chunk_id":"cshj8lbetkgjy","chunk_label":"unnamed-chunk-1","document_id":"286F9B27","expansion_state":0,"options":{"echo":true,"engine":"r","label":"unnamed-chunk-1"},"row":122,"row_count":1,"visible":true}],"chunk_rendered_width":700,"default_chunk_options":{"echo":true},"doc_write_time":1670992448,"working_dir":null}